nnspt/__init__.py
nnspt/__version__.py
nnspt/blocks/__init__.py
nnspt/blocks/encoders/__init__.py
nnspt/blocks/encoders/base.py
nnspt/blocks/encoders/builder.py
nnspt/blocks/encoders/misc.py
nnspt/blocks/encoders/converters/__init__.py
nnspt/blocks/encoders/converters/base.py
nnspt/blocks/encoders/converters/converter1d.py
nnspt/blocks/encoders/converters/convertertimm.py
nnspt/blocks/encoders/timm/__init__.py
nnspt/blocks/encoders/timm/convnext.py
nnspt/blocks/encoders/timm/efficientnet.py
nnspt/blocks/encoders/torchvision/__init__.py
nnspt/blocks/encoders/torchvision/densenet.py
nnspt/blocks/encoders/torchvision/resnet.py
nnspt/blocks/projectors/__init__.py
nnspt/blocks/projectors/heads.py
nnspt/classification/__init__.py
nnspt/pretraining/__init__.py
nnspt/pretraining/autoencoder.py
nnspt/segmentation/__init__.py
nnspt/segmentation/base.py
nnspt/segmentation/unet.py
tests/nnspt/__init__.py
tests/nnspt/blocks/__init__.py
tests/nnspt/blocks/encoders/__init__.py
tests/nnspt/blocks/encoders/timm/__init__.py
tests/nnspt/blocks/encoders/timm/test_convnext.py
tests/nnspt/blocks/encoders/timm/test_efficientnet.py
tests/nnspt/blocks/encoders/torchvision/__init__.py
tests/nnspt/blocks/encoders/torchvision/test_densenet.py
tests/nnspt/blocks/encoders/torchvision/test_resnet.py
tests/nnspt/pretraining/__init__.py
tests/nnspt/pretraining/test_autoencoder.py
tests/nnspt/segmentation/__init__.py
tests/nnspt/segmentation/test_unet.py
nnspt-0.0.1.dist-info/LICENSE
nnspt-0.0.1.dist-info/METADATA
nnspt-0.0.1.dist-info/WHEEL
nnspt-0.0.1.dist-info/top_level.txt
nnspt-0.0.1.dist-info/RECORD
